USL_USTC_lib/USL_USTC_lib.py
USL_USTC_lib/__init__.py
usl_ustc_lib-2025.6.1.dist-info/licenses/LICENSE
usl_ustc_lib-2025.6.1.dist-info/METADATA
usl_ustc_lib-2025.6.1.dist-info/WHEEL
usl_ustc_lib-2025.6.1.dist-info/top_level.txt
usl_ustc_lib-2025.6.1.dist-info/RECORD
