Metadata-Version: 2.4
Name: USL_USTC_lib
Version: 2025.6.1
Summary: Some useful functions for USL(ultra-stable laser)
Author-email: zxq985 <zxq985160104@163.com>
Project-URL: Homepage, https://github.com/ShinetingChu/USL-lib
Project-URL: Repository, https://github.com/ShinetingChu/USL-lib
Classifier: Programming Language :: Python :: 3
Classifier: License :: OSI Approved :: MIT License
Requires-Python: >=3.8
License-File: LICENSE
Dynamic: license-file
